fusionscript-stubs/__init__.pyi
fusionscript-stubs/fusionscript.pyi
fusionscript_stubs-20.2.2.dist-info/METADATA
fusionscript_stubs-20.2.2.dist-info/WHEEL
fusionscript_stubs-20.2.2.dist-info/top_level.txt
fusionscript_stubs-20.2.2.dist-info/RECORD
