Metadata-Version: 2.4
Name: fusionscript-stubs
Version: 20.2.2
Summary: DaVinci Resolve Python API stubs
Home-page: https://github.com/czukowski/fusionscript-stubs
Author: Korney Czukowski
Author-email: carbofos@seznam.cz
License: MIT
Dynamic: author
Dynamic: author-email
Dynamic: description
Dynamic: description-content-type
Dynamic: home-page
Dynamic: license
Dynamic: summary
